aioeffect/__init__.py
aioeffect/test_aioeffect.py
aioeffect-1.0.0.dist-info/DESCRIPTION.rst
aioeffect-1.0.0.dist-info/METADATA
aioeffect-1.0.0.dist-info/RECORD
aioeffect-1.0.0.dist-info/WHEEL
aioeffect-1.0.0.dist-info/metadata.json
aioeffect-1.0.0.dist-info/top_level.txt
