Metadata-Version: 2.0
Name: aioeffect
Version: 1.0.0
Summary: AsyncIO/Effect integration.
Home-page: https://github.com/touilleMan/aioeffect
Author: Emmanuel Leblond
Author-email: emmanuel.leblond@gmail.com
License: MIT
Keywords: aioeffect
Platform: UNKNOWN
Classifier: Development Status :: 2 - Pre-Alpha
Classifier: Intended Audience :: Developers
Classifier: License :: OSI Approved :: MIT License
Classifier: Natural Language :: English
Classifier: Programming Language :: Python :: 3
Classifier: Programming Language :: Python :: 3.5
Requires-Dist: effect
